setup.py
shinkenplugins/__init__.py
shinkenplugins.plugins.drupal_cron.egg-info/PKG-INFO
shinkenplugins.plugins.drupal_cron.egg-info/SOURCES.txt
shinkenplugins.plugins.drupal_cron.egg-info/dependency_links.txt
shinkenplugins.plugins.drupal_cron.egg-info/entry_points.txt
shinkenplugins.plugins.drupal_cron.egg-info/namespace_packages.txt
shinkenplugins.plugins.drupal_cron.egg-info/requires.txt
shinkenplugins.plugins.drupal_cron.egg-info/top_level.txt
shinkenplugins/plugins/__init__.py
shinkenplugins/plugins/drupal_cron/__init__.py
shinkenplugins/plugins/drupal_cron/drupal_cron.py